setup.py
PyGameTool/__init__.py
PyGameTool/button.py
PyGameTool/group.py
PyGameTool/image.py
PyGameTool/use01.py
PyGameTool.egg-info/PKG-INFO
PyGameTool.egg-info/SOURCES.txt
PyGameTool.egg-info/dependency_links.txt
PyGameTool.egg-info/requires.txt
PyGameTool.egg-info/top_level.txt