Metadata-Version: 2.1
Name: PyGameTool
Version: 1.0
Summary: some game tools about pygame
Author: pbcat2022
Author-email: yuyao_100804@outlook.com
